{"swagger":"2.0","info":{"description":"Api Documentation","version":"1.0","title":"Api Documentation","termsOfService":"urn:tos","contact":{},"license":{"name":"Apache 2.0","url":"http://www.apache.org/licenses/LICENSE-2.0"}},"host":"localhost:8080","basePath":"/","tags":[{"name":"Account Entity","description":"Simple Jpa Repository"},{"name":"Expense Entity","description":"Simple Jpa Repository"},{"name":"Income Entity","description":"Simple Jpa Repository"},{"name":"Transaction Entity","description":"Simple Jpa Repository"},{"name":"basic-error-controller","description":"Basic Error Controller"},{"name":"profile-controller","description":"Profile Controller"}],"paths":{"/accounts":{"get":{"tags":["Account Entity"],"summary":"findAllAccount","operationId":"findAllAccountUsingGET","produces":["application/json","application/hal+json","text/uri-list","application/x-spring-data-compact+json"],"parameters":[{"name":"page","in":"query","description":"page","required":false,"type":"string"},{"name":"size","in":"query","description":"size","required":false,"type":"string"},{"name":"sort","in":"query","description":"sort","required":false,"type":"string"}],"responses":{"200":{"description":"OK","schema":{"$ref":"#/definitions/Resources«Account»"}},"401":{"description":"Unauthorized"},"403":{"description":"Forbidden"},"404":{"description":"Not Found"}},"deprecated":false},"post":{"tags":["Account Entity"],"summary":"saveAccount","operationId":"saveAccountUsingPOST","consumes":["application/json"],"produces":["*/*"],"parameters":[{"in":"body","name":"body","description":"body","required":true,"schema":{"$ref":"#/definitions/Account"}}],"responses":{"200":{"description":"OK","schema":{"$ref":"#/definitions/Resource«Account»"}},"201":{"description":"Created"},"401":{"description":"Unauthorized"},"403":{"description":"Forbidden"},"404":{"description":"Not Found"}},"deprecated":false}},"/accounts/search/findByName":{"get":{"tags":["Account Entity"],"summary":"findByNameAccount","operationId":"findByNameAccountUsingGET","produces":["*/*"],"parameters":[{"name":"name","in":"query","description":"name","required":false,"type":"string"}],"responses":{"200":{"description":"OK","schema":{"$ref":"#/definitions/Resource«Account»"}},"401":{"description":"Unauthorized"},"403":{"description":"Forbidden"},"404":{"description":"Not Found"}},"deprecated":false}},"/accounts/search/findByNameIgnoreCase":{"get":{"tags":["Account Entity"],"summary":"findByNameIgnoreCaseAccount","operationId":"findByNameIgnoreCaseAccountUsingGET","produces":["*/*"],"parameters":[{"name":"name","in":"query","description":"name","required":false,"type":"string"}],"responses":{"200":{"description":"OK","schema":{"$ref":"#/definitions/Resource«Account»"}},"401":{"description":"Unauthorized"},"403":{"description":"Forbidden"},"404":{"description":"Not Found"}},"deprecated":false}},"/accounts/{id}":{"get":{"tags":["Account Entity"],"summary":"findByIdAccount","operationId":"findByIdAccountUsingGET","produces":["*/*"],"parameters":[{"name":"id","in":"path","description":"id","required":true,"type":"integer","format":"int32"}],"responses":{"200":{"description":"OK","schema":{"$ref":"#/definitions/Resource«Account»"}},"401":{"description":"Unauthorized"},"403":{"description":"Forbidden"},"404":{"description":"Not Found"}},"deprecated":false},"put":{"tags":["Account Entity"],"summary":"saveAccount","operationId":"saveAccountUsingPUT","consumes":["application/json"],"produces":["*/*"],"parameters":[{"in":"body","name":"body","description":"body","required":true,"schema":{"$ref":"#/definitions/Account"}},{"name":"id","in":"path","description":"id","required":true,"type":"integer","format":"int32"}],"responses":{"200":{"description":"OK","schema":{"$ref":"#/definitions/Resource«Account»"}},"201":{"description":"Created"},"401":{"description":"Unauthorized"},"403":{"description":"Forbidden"},"404":{"description":"Not Found"}},"deprecated":false},"delete":{"tags":["Account Entity"],"summary":"deleteAccount","operationId":"deleteAccountUsingDELETE","produces":["*/*"],"parameters":[{"name":"id","in":"path","description":"id","required":true,"type":"integer","format":"int32"}],"responses":{"200":{"description":"OK"},"204":{"description":"No Content"},"401":{"description":"Unauthorized"},"403":{"description":"Forbidden"}},"deprecated":false},"patch":{"tags":["Account Entity"],"summary":"saveAccount","operationId":"saveAccountUsingPATCH","consumes":["application/json"],"produces":["*/*"],"parameters":[{"in":"body","name":"body","description":"body","required":true,"schema":{"$ref":"#/definitions/Account"}},{"name":"id","in":"path","description":"id","required":true,"type":"integer","format":"int32"}],"responses":{"200":{"description":"OK","schema":{"$ref":"#/definitions/Resource«Account»"}},"204":{"description":"No Content"},"401":{"description":"Unauthorized"},"403":{"description":"Forbidden"}},"deprecated":false}},"/error":{"get":{"tags":["basic-error-controller"],"summary":"error","operationId":"errorUsingGET","produces":["*/*"],"responses":{"200":{"description":"OK","schema":{"type":"object","additionalProperties":{"type":"object"}}},"401":{"description":"Unauthorized"},"403":{"description":"Forbidden"},"404":{"description":"Not Found"}},"deprecated":false},"head":{"tags":["basic-error-controller"],"summary":"error","operationId":"errorUsingHEAD","consumes":["application/json"],"produces":["*/*"],"responses":{"200":{"description":"OK","schema":{"type":"object","additionalProperties":{"type":"object"}}},"204":{"description":"No Content"},"401":{"description":"Unauthorized"},"403":{"description":"Forbidden"}},"deprecated":false},"post":{"tags":["basic-error-controller"],"summary":"error","operationId":"errorUsingPOST","consumes":["application/json"],"produces":["*/*"],"responses":{"200":{"description":"OK","schema":{"type":"object","additionalProperties":{"type":"object"}}},"201":{"description":"Created"},"401":{"description":"Unauthorized"},"403":{"description":"Forbidden"},"404":{"description":"Not Found"}},"deprecated":false},"put":{"tags":["basic-error-controller"],"summary":"error","operationId":"errorUsingPUT","consumes":["application/json"],"produces":["*/*"],"responses":{"200":{"description":"OK","schema":{"type":"object","additionalProperties":{"type":"object"}}},"201":{"description":"Created"},"401":{"description":"Unauthorized"},"403":{"description":"Forbidden"},"404":{"description":"Not Found"}},"deprecated":false},"delete":{"tags":["basic-error-controller"],"summary":"error","operationId":"errorUsingDELETE","produces":["*/*"],"responses":{"200":{"description":"OK","schema":{"type":"object","additionalProperties":{"type":"object"}}},"204":{"description":"No Content"},"401":{"description":"Unauthorized"},"403":{"description":"Forbidden"}},"deprecated":false},"options":{"tags":["basic-error-controller"],"summary":"error","operationId":"errorUsingOPTIONS","consumes":["application/json"],"produces":["*/*"],"responses":{"200":{"description":"OK","schema":{"type":"object","additionalProperties":{"type":"object"}}},"204":{"description":"No Content"},"401":{"description":"Unauthorized"},"403":{"description":"Forbidden"}},"deprecated":false},"patch":{"tags":["basic-error-controller"],"summary":"error","operationId":"errorUsingPATCH","consumes":["application/json"],"produces":["*/*"],"responses":{"200":{"description":"OK","schema":{"type":"object","additionalProperties":{"type":"object"}}},"204":{"description":"No Content"},"401":{"description":"Unauthorized"},"403":{"description":"Forbidden"}},"deprecated":false}},"/expenses":{"get":{"tags":["Expense Entity"],"summary":"findAllExpense","operationId":"findAllExpenseUsingGET","produces":["application/json","application/hal+json","text/uri-list","application/x-spring-data-compact+json"],"parameters":[{"name":"page","in":"query","description":"page","required":false,"type":"string"},{"name":"size","in":"query","description":"size","required":false,"type":"string"},{"name":"sort","in":"query","description":"sort","required":false,"type":"string"}],"responses":{"200":{"description":"OK","schema":{"$ref":"#/definitions/Resources«Expense»"}},"401":{"description":"Unauthorized"},"403":{"description":"Forbidden"},"404":{"description":"Not Found"}},"deprecated":false},"post":{"tags":["Expense Entity"],"summary":"saveExpense","operationId":"saveExpenseUsingPOST","consumes":["application/json"],"produces":["*/*"],"parameters":[{"in":"body","name":"body","description":"body","required":true,"schema":{"$ref":"#/definitions/Expense"}}],"responses":{"200":{"description":"OK","schema":{"$ref":"#/definitions/Resource«Expense»"}},"201":{"description":"Created"},"401":{"description":"Unauthorized"},"403":{"description":"Forbidden"},"404":{"description":"Not Found"}},"deprecated":false}},"/expenses/search/findAllCompleteExpensesByAccount":{"get":{"tags":["Expense Entity"],"summary":"findAllCompleteExpensesByAccountExpense","operationId":"findAllCompleteExpensesByAccountExpenseUsingGET","produces":["*/*"],"parameters":[{"name":"account","in":"query","description":"account","required":false,"type":"string"}],"responses":{"200":{"description":"OK","schema":{"$ref":"#/definitions/Resources«Expense»"}},"401":{"description":"Unauthorized"},"403":{"description":"Forbidden"},"404":{"description":"Not Found"}},"deprecated":false}},"/expenses/search/findAllIncompleteExpensesByAccount":{"get":{"tags":["Expense Entity"],"summary":"findAllIncompleteExpensesByAccountExpense","operationId":"findAllIncompleteExpensesByAccountExpenseUsingGET","produces":["*/*"],"parameters":[{"name":"account","in":"query","description":"account","required":false,"type":"string"}],"responses":{"200":{"description":"OK","schema":{"$ref":"#/definitions/Resources«Expense»"}},"401":{"description":"Unauthorized"},"403":{"description":"Forbidden"},"404":{"description":"Not Found"}},"deprecated":false}},"/expenses/search/findByAccountName":{"get":{"tags":["Expense Entity"],"summary":"findByAccountNameExpense","operationId":"findByAccountNameExpenseUsingGET","produces":["*/*"],"parameters":[{"name":"accountName","in":"query","description":"accountName","required":false,"type":"string"}],"responses":{"200":{"description":"OK","schema":{"$ref":"#/definitions/Resources«Expense»"}},"401":{"description":"Unauthorized"},"403":{"description":"Forbidden"},"404":{"description":"Not Found"}},"deprecated":false}},"/expenses/search/findOneByAccountAndTitle":{"get":{"tags":["Expense Entity"],"summary":"findOneByAccountAndTitleExpense","operationId":"findOneByAccountAndTitleExpenseUsingGET","produces":["*/*"],"parameters":[{"name":"name","in":"query","required":false,"type":"string"},{"name":"title","in":"query","description":"title","required":false,"type":"string"}],"responses":{"200":{"description":"OK","schema":{"$ref":"#/definitions/Resource«Expense»"}},"401":{"description":"Unauthorized"},"403":{"description":"Forbidden"},"404":{"description":"Not Found"}},"deprecated":false}},"/expenses/{id}":{"get":{"tags":["Expense Entity"],"summary":"findByIdExpense","operationId":"findByIdExpenseUsingGET","produces":["*/*"],"parameters":[{"name":"id","in":"path","description":"id","required":true,"type":"integer","format":"int32"}],"responses":{"200":{"description":"OK","schema":{"$ref":"#/definitions/Resource«Expense»"}},"401":{"description":"Unauthorized"},"403":{"description":"Forbidden"},"404":{"description":"Not Found"}},"deprecated":false},"put":{"tags":["Expense Entity"],"summary":"saveExpense","operationId":"saveExpenseUsingPUT","consumes":["application/json"],"produces":["*/*"],"parameters":[{"in":"body","name":"body","description":"body","required":true,"schema":{"$ref":"#/definitions/Expense"}},{"name":"id","in":"path","description":"id","required":true,"type":"integer","format":"int32"}],"responses":{"200":{"description":"OK","schema":{"$ref":"#/definitions/Resource«Expense»"}},"201":{"description":"Created"},"401":{"description":"Unauthorized"},"403":{"description":"Forbidden"},"404":{"description":"Not Found"}},"deprecated":false},"delete":{"tags":["Expense Entity"],"summary":"deleteExpense","operationId":"deleteExpenseUsingDELETE","produces":["*/*"],"parameters":[{"name":"id","in":"path","description":"id","required":true,"type":"integer","format":"int32"}],"responses":{"200":{"description":"OK"},"204":{"description":"No Content"},"401":{"description":"Unauthorized"},"403":{"description":"Forbidden"}},"deprecated":false},"patch":{"tags":["Expense Entity"],"summary":"saveExpense","operationId":"saveExpenseUsingPATCH","consumes":["application/json"],"produces":["*/*"],"parameters":[{"in":"body","name":"body","description":"body","required":true,"schema":{"$ref":"#/definitions/Expense"}},{"name":"id","in":"path","description":"id","required":true,"type":"integer","format":"int32"}],"responses":{"200":{"description":"OK","schema":{"$ref":"#/definitions/Resource«Expense»"}},"204":{"description":"No Content"},"401":{"description":"Unauthorized"},"403":{"description":"Forbidden"}},"deprecated":false}},"/expenses/{id}/account":{"get":{"tags":["Expense Entity"],"summary":"expenseAccount","operationId":"expenseAccountUsingGET","produces":["application/hal+json"],"parameters":[{"name":"id","in":"path","description":"id","required":true,"type":"integer","format":"int32"}],"responses":{"200":{"description":"OK","schema":{"$ref":"#/definitions/Resource«Account»"}},"401":{"description":"Unauthorized"},"403":{"description":"Forbidden"},"404":{"description":"Not Found"}},"deprecated":false},"post":{"tags":["Expense Entity"],"summary":"expenseAccount","operationId":"expenseAccountUsingPOST","consumes":["text/uri-list","application/x-spring-data-compact+json"],"produces":["*/*"],"parameters":[{"in":"body","name":"body","description":"body","required":true,"schema":{"type":"string"}},{"name":"id","in":"path","description":"id","required":true,"type":"integer","format":"int32"}],"responses":{"200":{"description":"OK","schema":{"$ref":"#/definitions/Resource«Account»"}},"201":{"description":"Created"},"401":{"description":"Unauthorized"},"403":{"description":"Forbidden"},"404":{"description":"Not Found"}},"deprecated":false},"put":{"tags":["Expense Entity"],"summary":"expenseAccount","operationId":"expenseAccountUsingPUT","consumes":["text/uri-list","application/x-spring-data-compact+json"],"produces":["*/*"],"parameters":[{"in":"body","name":"body","description":"body","required":true,"schema":{"type":"string"}},{"name":"id","in":"path","description":"id","required":true,"type":"integer","format":"int32"}],"responses":{"200":{"description":"OK","schema":{"$ref":"#/definitions/Resource«Account»"}},"201":{"description":"Created"},"401":{"description":"Unauthorized"},"403":{"description":"Forbidden"},"404":{"description":"Not Found"}},"deprecated":false},"delete":{"tags":["Expense Entity"],"summary":"expenseAccount","operationId":"expenseAccountUsingDELETE","consumes":["text/uri-list","application/x-spring-data-compact+json"],"produces":["*/*"],"parameters":[{"name":"id","in":"path","description":"id","required":true,"type":"integer","format":"int32"}],"responses":{"200":{"description":"OK"},"204":{"description":"No Content"},"401":{"description":"Unauthorized"},"403":{"description":"Forbidden"}},"deprecated":false},"patch":{"tags":["Expense Entity"],"summary":"expenseAccount","operationId":"expenseAccountUsingPATCH","consumes":["text/uri-list","application/x-spring-data-compact+json"],"produces":["*/*"],"parameters":[{"in":"body","name":"body","description":"body","required":true,"schema":{"type":"string"}},{"name":"id","in":"path","description":"id","required":true,"type":"integer","format":"int32"}],"responses":{"200":{"description":"OK","schema":{"$ref":"#/definitions/Resource«Account»"}},"204":{"description":"No Content"},"401":{"description":"Unauthorized"},"403":{"description":"Forbidden"}},"deprecated":false}},"/incomes":{"get":{"tags":["Income Entity"],"summary":"findAllIncome","operationId":"findAllIncomeUsingGET","produces":["application/json","application/hal+json","text/uri-list","application/x-spring-data-compact+json"],"parameters":[{"name":"page","in":"query","description":"page","required":false,"type":"string"},{"name":"size","in":"query","description":"size","required":false,"type":"string"},{"name":"sort","in":"query","description":"sort","required":false,"type":"string"}],"responses":{"200":{"description":"OK","schema":{"$ref":"#/definitions/Resources«Income»"}},"401":{"description":"Unauthorized"},"403":{"description":"Forbidden"},"404":{"description":"Not Found"}},"deprecated":false},"post":{"tags":["Income Entity"],"summary":"saveIncome","operationId":"saveIncomeUsingPOST","consumes":["application/json"],"produces":["*/*"],"parameters":[{"in":"body","name":"body","description":"body","required":true,"schema":{"$ref":"#/definitions/Income"}}],"responses":{"200":{"description":"OK","schema":{"$ref":"#/definitions/Resource«Income»"}},"201":{"description":"Created"},"401":{"description":"Unauthorized"},"403":{"description":"Forbidden"},"404":{"description":"Not Found"}},"deprecated":false}},"/incomes/search/findAllByAccount":{"get":{"tags":["Income Entity"],"summary":"findAllByAccountIncome","operationId":"findAllByAccountIncomeUsingGET","produces":["*/*"],"parameters":[{"name":"account","in":"query","description":"account","required":false,"type":"string"}],"responses":{"200":{"description":"OK","schema":{"$ref":"#/definitions/Resources«Income»"}},"401":{"description":"Unauthorized"},"403":{"description":"Forbidden"},"404":{"description":"Not Found"}},"deprecated":false}},"/incomes/search/findAllWithRemainingCreditByAccount":{"get":{"tags":["Income Entity"],"summary":"findAllWithRemainingCreditByAccountIncome","operationId":"findAllWithRemainingCreditByAccountIncomeUsingGET","produces":["*/*"],"parameters":[{"name":"account","in":"query","description":"account","required":false,"type":"string"}],"responses":{"200":{"description":"OK","schema":{"$ref":"#/definitions/Resources«Income»"}},"401":{"description":"Unauthorized"},"403":{"description":"Forbidden"},"404":{"description":"Not Found"}},"deprecated":false}},"/incomes/search/findByAccountName":{"get":{"tags":["Income Entity"],"summary":"findByAccountNameIncome","operationId":"findByAccountNameIncomeUsingGET","produces":["*/*"],"parameters":[{"name":"accountName","in":"query","description":"accountName","required":false,"type":"string"}],"responses":{"200":{"description":"OK","schema":{"$ref":"#/definitions/Resources«Income»"}},"401":{"description":"Unauthorized"},"403":{"description":"Forbidden"},"404":{"description":"Not Found"}},"deprecated":false}},"/incomes/{id}":{"get":{"tags":["Income Entity"],"summary":"findByIdIncome","operationId":"findByIdIncomeUsingGET","produces":["*/*"],"parameters":[{"name":"id","in":"path","description":"id","required":true,"type":"integer","format":"int32"}],"responses":{"200":{"description":"OK","schema":{"$ref":"#/definitions/Resource«Income»"}},"401":{"description":"Unauthorized"},"403":{"description":"Forbidden"},"404":{"description":"Not Found"}},"deprecated":false},"put":{"tags":["Income Entity"],"summary":"saveIncome","operationId":"saveIncomeUsingPUT","consumes":["application/json"],"produces":["*/*"],"parameters":[{"in":"body","name":"body","description":"body","required":true,"schema":{"$ref":"#/definitions/Income"}},{"name":"id","in":"path","description":"id","required":true,"type":"integer","format":"int32"}],"responses":{"200":{"description":"OK","schema":{"$ref":"#/definitions/Resource«Income»"}},"201":{"description":"Created"},"401":{"description":"Unauthorized"},"403":{"description":"Forbidden"},"404":{"description":"Not Found"}},"deprecated":false},"delete":{"tags":["Income Entity"],"summary":"deleteIncome","operationId":"deleteIncomeUsingDELETE","produces":["*/*"],"parameters":[{"name":"id","in":"path","description":"id","required":true,"type":"integer","format":"int32"}],"responses":{"200":{"description":"OK"},"204":{"description":"No Content"},"401":{"description":"Unauthorized"},"403":{"description":"Forbidden"}},"deprecated":false},"patch":{"tags":["Income Entity"],"summary":"saveIncome","operationId":"saveIncomeUsingPATCH","consumes":["application/json"],"produces":["*/*"],"parameters":[{"in":"body","name":"body","description":"body","required":true,"schema":{"$ref":"#/definitions/Income"}},{"name":"id","in":"path","description":"id","required":true,"type":"integer","format":"int32"}],"responses":{"200":{"description":"OK","schema":{"$ref":"#/definitions/Resource«Income»"}},"204":{"description":"No Content"},"401":{"description":"Unauthorized"},"403":{"description":"Forbidden"}},"deprecated":false}},"/incomes/{id}/account":{"get":{"tags":["Income Entity"],"summary":"incomeAccount","operationId":"incomeAccountUsingGET","produces":["application/hal+json"],"parameters":[{"name":"id","in":"path","description":"id","required":true,"type":"integer","format":"int32"}],"responses":{"200":{"description":"OK","schema":{"$ref":"#/definitions/Resource«Account»"}},"401":{"description":"Unauthorized"},"403":{"description":"Forbidden"},"404":{"description":"Not Found"}},"deprecated":false},"post":{"tags":["Income Entity"],"summary":"incomeAccount","operationId":"incomeAccountUsingPOST","consumes":["text/uri-list","application/x-spring-data-compact+json"],"produces":["*/*"],"parameters":[{"in":"body","name":"body","description":"body","required":true,"schema":{"type":"string"}},{"name":"id","in":"path","description":"id","required":true,"type":"integer","format":"int32"}],"responses":{"200":{"description":"OK","schema":{"$ref":"#/definitions/Resource«Account»"}},"201":{"description":"Created"},"401":{"description":"Unauthorized"},"403":{"description":"Forbidden"},"404":{"description":"Not Found"}},"deprecated":false},"put":{"tags":["Income Entity"],"summary":"incomeAccount","operationId":"incomeAccountUsingPUT","consumes":["text/uri-list","application/x-spring-data-compact+json"],"produces":["*/*"],"parameters":[{"in":"body","name":"body","description":"body","required":true,"schema":{"type":"string"}},{"name":"id","in":"path","description":"id","required":true,"type":"integer","format":"int32"}],"responses":{"200":{"description":"OK","schema":{"$ref":"#/definitions/Resource«Account»"}},"201":{"description":"Created"},"401":{"description":"Unauthorized"},"403":{"description":"Forbidden"},"404":{"description":"Not Found"}},"deprecated":false},"delete":{"tags":["Income Entity"],"summary":"incomeAccount","operationId":"incomeAccountUsingDELETE","consumes":["text/uri-list","application/x-spring-data-compact+json"],"produces":["*/*"],"parameters":[{"name":"id","in":"path","description":"id","required":true,"type":"integer","format":"int32"}],"responses":{"200":{"description":"OK"},"204":{"description":"No Content"},"401":{"description":"Unauthorized"},"403":{"description":"Forbidden"}},"deprecated":false},"patch":{"tags":["Income Entity"],"summary":"incomeAccount","operationId":"incomeAccountUsingPATCH","consumes":["text/uri-list","application/x-spring-data-compact+json"],"produces":["*/*"],"parameters":[{"in":"body","name":"body","description":"body","required":true,"schema":{"type":"string"}},{"name":"id","in":"path","description":"id","required":true,"type":"integer","format":"int32"}],"responses":{"200":{"description":"OK","schema":{"$ref":"#/definitions/Resource«Account»"}},"204":{"description":"No Content"},"401":{"description":"Unauthorized"},"403":{"description":"Forbidden"}},"deprecated":false}},"/profile":{"get":{"tags":["profile-controller"],"summary":"listAllFormsOfMetadata","operationId":"listAllFormsOfMetadataUsingGET","produces":["*/*"],"responses":{"200":{"description":"OK","schema":{"$ref":"#/definitions/ResourceSupport"}},"401":{"description":"Unauthorized"},"403":{"description":"Forbidden"},"404":{"description":"Not Found"}},"deprecated":false},"options":{"tags":["profile-controller"],"summary":"profileOptions","operationId":"profileOptionsUsingOPTIONS","consumes":["application/json"],"produces":["*/*"],"responses":{"200":{"description":"OK","schema":{"type":"object"}},"204":{"description":"No Content"},"401":{"description":"Unauthorized"},"403":{"description":"Forbidden"}},"deprecated":false}},"/transactions":{"get":{"tags":["Transaction Entity"],"summary":"findAllTransaction","operationId":"findAllTransactionUsingGET","produces":["application/json","application/hal+json","text/uri-list","application/x-spring-data-compact+json"],"parameters":[{"name":"page","in":"query","description":"page","required":false,"type":"string"},{"name":"size","in":"query","description":"size","required":false,"type":"string"},{"name":"sort","in":"query","description":"sort","required":false,"type":"string"}],"responses":{"200":{"description":"OK","schema":{"$ref":"#/definitions/Resources«Transaction»"}},"401":{"description":"Unauthorized"},"403":{"description":"Forbidden"},"404":{"description":"Not Found"}},"deprecated":false},"post":{"tags":["Transaction Entity"],"summary":"saveTransaction","operationId":"saveTransactionUsingPOST","consumes":["application/json"],"produces":["*/*"],"parameters":[{"in":"body","name":"body","description":"body","required":true,"schema":{"$ref":"#/definitions/Transaction"}}],"responses":{"200":{"description":"OK","schema":{"$ref":"#/definitions/Resource«Transaction»"}},"201":{"description":"Created"},"401":{"description":"Unauthorized"},"403":{"description":"Forbidden"},"404":{"description":"Not Found"}},"deprecated":false}},"/transactions/search/findAllByFromAccount":{"get":{"tags":["Transaction Entity"],"summary":"findAllByFromAccountTransaction","operationId":"findAllByFromAccountTransactionUsingGET","produces":["*/*"],"parameters":[{"name":"account","in":"query","description":"account","required":false,"type":"string"}],"responses":{"200":{"description":"OK","schema":{"$ref":"#/definitions/Resources«Transaction»"}},"401":{"description":"Unauthorized"},"403":{"description":"Forbidden"},"404":{"description":"Not Found"}},"deprecated":false}},"/transactions/{id}":{"get":{"tags":["Transaction Entity"],"summary":"findByIdTransaction","operationId":"findByIdTransactionUsingGET","produces":["*/*"],"parameters":[{"name":"id","in":"path","description":"id","required":true,"type":"integer","format":"int32"}],"responses":{"200":{"description":"OK","schema":{"$ref":"#/definitions/Resource«Transaction»"}},"401":{"description":"Unauthorized"},"403":{"description":"Forbidden"},"404":{"description":"Not Found"}},"deprecated":false},"put":{"tags":["Transaction Entity"],"summary":"saveTransaction","operationId":"saveTransactionUsingPUT","consumes":["application/json"],"produces":["*/*"],"parameters":[{"in":"body","name":"body","description":"body","required":true,"schema":{"$ref":"#/definitions/Transaction"}},{"name":"id","in":"path","description":"id","required":true,"type":"integer","format":"int32"}],"responses":{"200":{"description":"OK","schema":{"$ref":"#/definitions/Resource«Transaction»"}},"201":{"description":"Created"},"401":{"description":"Unauthorized"},"403":{"description":"Forbidden"},"404":{"description":"Not Found"}},"deprecated":false},"delete":{"tags":["Transaction Entity"],"summary":"deleteTransaction","operationId":"deleteTransactionUsingDELETE","produces":["*/*"],"parameters":[{"name":"id","in":"path","description":"id","required":true,"type":"integer","format":"int32"}],"responses":{"200":{"description":"OK"},"204":{"description":"No Content"},"401":{"description":"Unauthorized"},"403":{"description":"Forbidden"}},"deprecated":false},"patch":{"tags":["Transaction Entity"],"summary":"saveTransaction","operationId":"saveTransactionUsingPATCH","consumes":["application/json"],"produces":["*/*"],"parameters":[{"in":"body","name":"body","description":"body","required":true,"schema":{"$ref":"#/definitions/Transaction"}},{"name":"id","in":"path","description":"id","required":true,"type":"integer","format":"int32"}],"responses":{"200":{"description":"OK","schema":{"$ref":"#/definitions/Resource«Transaction»"}},"204":{"description":"No Content"},"401":{"description":"Unauthorized"},"403":{"description":"Forbidden"}},"deprecated":false}},"/transactions/{id}/from":{"get":{"tags":["Transaction Entity"],"summary":"transactionFrom","operationId":"transactionFromUsingGET","produces":["application/hal+json"],"parameters":[{"name":"id","in":"path","description":"id","required":true,"type":"integer","format":"int32"}],"responses":{"200":{"description":"OK","schema":{"$ref":"#/definitions/Resource«Income»"}},"401":{"description":"Unauthorized"},"403":{"description":"Forbidden"},"404":{"description":"Not Found"}},"deprecated":false},"post":{"tags":["Transaction Entity"],"summary":"transactionFrom","operationId":"transactionFromUsingPOST","consumes":["text/uri-list","application/x-spring-data-compact+json"],"produces":["*/*"],"parameters":[{"in":"body","name":"body","description":"body","required":true,"schema":{"type":"string"}},{"name":"id","in":"path","description":"id","required":true,"type":"integer","format":"int32"}],"responses":{"200":{"description":"OK","schema":{"$ref":"#/definitions/Resource«Income»"}},"201":{"description":"Created"},"401":{"description":"Unauthorized"},"403":{"description":"Forbidden"},"404":{"description":"Not Found"}},"deprecated":false},"put":{"tags":["Transaction Entity"],"summary":"transactionFrom","operationId":"transactionFromUsingPUT","consumes":["text/uri-list","application/x-spring-data-compact+json"],"produces":["*/*"],"parameters":[{"in":"body","name":"body","description":"body","required":true,"schema":{"type":"string"}},{"name":"id","in":"path","description":"id","required":true,"type":"integer","format":"int32"}],"responses":{"200":{"description":"OK","schema":{"$ref":"#/definitions/Resource«Income»"}},"201":{"description":"Created"},"401":{"description":"Unauthorized"},"403":{"description":"Forbidden"},"404":{"description":"Not Found"}},"deprecated":false},"delete":{"tags":["Transaction Entity"],"summary":"transactionFrom","operationId":"transactionFromUsingDELETE","consumes":["text/uri-list","application/x-spring-data-compact+json"],"produces":["*/*"],"parameters":[{"name":"id","in":"path","description":"id","required":true,"type":"integer","format":"int32"}],"responses":{"200":{"description":"OK"},"204":{"description":"No Content"},"401":{"description":"Unauthorized"},"403":{"description":"Forbidden"}},"deprecated":false},"patch":{"tags":["Transaction Entity"],"summary":"transactionFrom","operationId":"transactionFromUsingPATCH","consumes":["text/uri-list","application/x-spring-data-compact+json"],"produces":["*/*"],"parameters":[{"in":"body","name":"body","description":"body","required":true,"schema":{"type":"string"}},{"name":"id","in":"path","description":"id","required":true,"type":"integer","format":"int32"}],"responses":{"200":{"description":"OK","schema":{"$ref":"#/definitions/Resource«Income»"}},"204":{"description":"No Content"},"401":{"description":"Unauthorized"},"403":{"description":"Forbidden"}},"deprecated":false}},"/transactions/{id}/to":{"get":{"tags":["Transaction Entity"],"summary":"transactionTo","operationId":"transactionToUsingGET","produces":["application/hal+json"],"parameters":[{"name":"id","in":"path","description":"id","required":true,"type":"integer","format":"int32"}],"responses":{"200":{"description":"OK","schema":{"$ref":"#/definitions/Resource«Expense»"}},"401":{"description":"Unauthorized"},"403":{"description":"Forbidden"},"404":{"description":"Not Found"}},"deprecated":false},"post":{"tags":["Transaction Entity"],"summary":"transactionTo","operationId":"transactionToUsingPOST","consumes":["text/uri-list","application/x-spring-data-compact+json"],"produces":["*/*"],"parameters":[{"in":"body","name":"body","description":"body","required":true,"schema":{"type":"string"}},{"name":"id","in":"path","description":"id","required":true,"type":"integer","format":"int32"}],"responses":{"200":{"description":"OK","schema":{"$ref":"#/definitions/Resource«Expense»"}},"201":{"description":"Created"},"401":{"description":"Unauthorized"},"403":{"description":"Forbidden"},"404":{"description":"Not Found"}},"deprecated":false},"put":{"tags":["Transaction Entity"],"summary":"transactionTo","operationId":"transactionToUsingPUT","consumes":["text/uri-list","application/x-spring-data-compact+json"],"produces":["*/*"],"parameters":[{"in":"body","name":"body","description":"body","required":true,"schema":{"type":"string"}},{"name":"id","in":"path","description":"id","required":true,"type":"integer","format":"int32"}],"responses":{"200":{"description":"OK","schema":{"$ref":"#/definitions/Resource«Expense»"}},"201":{"description":"Created"},"401":{"description":"Unauthorized"},"403":{"description":"Forbidden"},"404":{"description":"Not Found"}},"deprecated":false},"delete":{"tags":["Transaction Entity"],"summary":"transactionTo","operationId":"transactionToUsingDELETE","consumes":["text/uri-list","application/x-spring-data-compact+json"],"produces":["*/*"],"parameters":[{"name":"id","in":"path","description":"id","required":true,"type":"integer","format":"int32"}],"responses":{"200":{"description":"OK"},"204":{"description":"No Content"},"401":{"description":"Unauthorized"},"403":{"description":"Forbidden"}},"deprecated":false},"patch":{"tags":["Transaction Entity"],"summary":"transactionTo","operationId":"transactionToUsingPATCH","consumes":["text/uri-list","application/x-spring-data-compact+json"],"produces":["*/*"],"parameters":[{"in":"body","name":"body","description":"body","required":true,"schema":{"type":"string"}},{"name":"id","in":"path","description":"id","required":true,"type":"integer","format":"int32"}],"responses":{"200":{"description":"OK","schema":{"$ref":"#/definitions/Resource«Expense»"}},"204":{"description":"No Content"},"401":{"description":"Unauthorized"},"403":{"description":"Forbidden"}},"deprecated":false}}},"definitions":{"Account":{"type":"object","properties":{"name":{"type":"string"}},"title":"Account"},"EmbeddedCollection«Account»":{"type":"object","required":["accounts"],"properties":{"accounts":{"type":"array","description":"Resource collection","items":{"$ref":"#/definitions/Account"}}},"title":"EmbeddedCollection«Account»","xml":{"name":"content","wrapped":true},"description":"Embedded collection of Account"},"EmbeddedCollection«Expense»":{"type":"object","required":["expenses"],"properties":{"expenses":{"type":"array","description":"Resource collection","items":{"$ref":"#/definitions/Expense"}}},"title":"EmbeddedCollection«Expense»","description":"Embedded collection of Expense"},"EmbeddedCollection«Income»":{"type":"object","required":["incomes"],"properties":{"incomes":{"type":"array","description":"Resource collection","items":{"$ref":"#/definitions/Income"}}},"title":"EmbeddedCollection«Income»","description":"Embedded collection of Income"},"EmbeddedCollection«Transaction»":{"type":"object","required":["transactions"],"properties":{"transactions":{"type":"array","description":"Resource collection","items":{"$ref":"#/definitions/Transaction"}}},"title":"EmbeddedCollection«Transaction»","description":"Embedded collection of Transaction"},"Expense":{"type":"object","properties":{"account":{"$ref":"#/definitions/Account"},"amount":{"type":"integer","format":"int32"},"balance":{"type":"integer","format":"int32"},"complete":{"type":"boolean"},"title":{"type":"string"}},"title":"Expense"},"Income":{"type":"object","properties":{"account":{"$ref":"#/definitions/Account"},"amount":{"type":"integer","format":"int32"},"title":{"type":"string"}},"title":"Income"},"Link":{"type":"object","properties":{"deprecation":{"type":"string","xml":{"name":"deprecation","attribute":true,"wrapped":false}},"href":{"type":"string","xml":{"name":"href","attribute":true,"wrapped":false}},"hreflang":{"type":"string","xml":{"name":"hreflang","attribute":true,"wrapped":false}},"media":{"type":"string","xml":{"name":"media","attribute":true,"wrapped":false}},"rel":{"type":"string","xml":{"name":"rel","attribute":true,"wrapped":false}},"templated":{"type":"boolean"},"title":{"type":"string","xml":{"name":"title","attribute":true,"wrapped":false}},"type":{"type":"string","xml":{"name":"type","attribute":true,"wrapped":false}}},"title":"Link","xml":{"name":"link","namespace":"http://www.w3.org/2005/Atom","attribute":false,"wrapped":false}},"ModelAndView":{"type":"object","properties":{"empty":{"type":"boolean"},"model":{"type":"object"},"modelMap":{"type":"object","additionalProperties":{"type":"object"}},"reference":{"type":"boolean"},"status":{"type":"string","enum":["100","101","102","103","200","201","202","203","204","205","206","207","208","226","300","301","302","303","304","305","307","308","400","401","402","403","404","405","406","407","408","409","410","411","412","413","414","415","416","417","418","419","420","421","422","423","424","426","428","429","431","451","500","501","502","503","504","505","506","507","508","509","510","511"]},"view":{"$ref":"#/definitions/View"},"viewName":{"type":"string"}},"title":"ModelAndView"},"ResourceSupport":{"type":"object","properties":{"links":{"type":"array","xml":{"name":"link","namespace":"http://www.w3.org/2005/Atom","attribute":false,"wrapped":false},"items":{"$ref":"#/definitions/Link"}}},"title":"ResourceSupport"},"Resources«Account»":{"type":"object","required":["_embedded","_links"],"properties":{"_embedded":{"$ref":"#/definitions/EmbeddedCollection«Account»"},"_links":{"type":"object","description":"Link collection","additionalProperties":{"$ref":"#/definitions/Link"}}},"title":"Resources«Account»","xml":{"name":"entities","attribute":false,"wrapped":false},"description":"Resources of Account"},"Resources«Expense»":{"type":"object","required":["_embedded","_links"],"properties":{"_embedded":{"$ref":"#/definitions/EmbeddedCollection«Expense»"},"_links":{"type":"object","description":"Link collection","additionalProperties":{"$ref":"#/definitions/Link"}}},"title":"Resources«Expense»","description":"Resources of Expense"},"Resources«Income»":{"type":"object","required":["_embedded","_links"],"properties":{"_embedded":{"$ref":"#/definitions/EmbeddedCollection«Income»"},"_links":{"type":"object","description":"Link collection","additionalProperties":{"$ref":"#/definitions/Link"}}},"title":"Resources«Income»","description":"Resources of Income"},"Resources«Transaction»":{"type":"object","required":["_embedded","_links"],"properties":{"_embedded":{"$ref":"#/definitions/EmbeddedCollection«Transaction»"},"_links":{"type":"object","description":"Link collection","additionalProperties":{"$ref":"#/definitions/Link"}}},"title":"Resources«Transaction»","description":"Resources of Transaction"},"Resource«Account»":{"type":"object","properties":{"links":{"type":"array","xml":{"name":"link","namespace":"http://www.w3.org/2005/Atom","attribute":false,"wrapped":false},"items":{"$ref":"#/definitions/Link"}},"name":{"type":"string"}},"title":"Resource«Account»"},"Resource«Expense»":{"type":"object","properties":{"account":{"$ref":"#/definitions/Account"},"amount":{"type":"integer","format":"int32"},"balance":{"type":"integer","format":"int32"},"complete":{"type":"boolean"},"links":{"type":"array","xml":{"name":"link","namespace":"http://www.w3.org/2005/Atom","attribute":false,"wrapped":false},"items":{"$ref":"#/definitions/Link"}},"title":{"type":"string"}},"title":"Resource«Expense»"},"Resource«Income»":{"type":"object","properties":{"account":{"$ref":"#/definitions/Account"},"amount":{"type":"integer","format":"int32"},"links":{"type":"array","xml":{"name":"link","namespace":"http://www.w3.org/2005/Atom","attribute":false,"wrapped":false},"items":{"$ref":"#/definitions/Link"}},"title":{"type":"string"}},"title":"Resource«Income»"},"Resource«Transaction»":{"type":"object","properties":{"from":{"$ref":"#/definitions/Income"},"links":{"type":"array","xml":{"name":"link","namespace":"http://www.w3.org/2005/Atom","attribute":false,"wrapped":false},"items":{"$ref":"#/definitions/Link"}},"to":{"$ref":"#/definitions/Expense"},"value":{"type":"integer","format":"int32"}},"title":"Resource«Transaction»"},"Transaction":{"type":"object","properties":{"from":{"$ref":"#/definitions/Income"},"to":{"$ref":"#/definitions/Expense"},"value":{"type":"integer","format":"int32"}},"title":"Transaction"},"View":{"type":"object","properties":{"contentType":{"type":"string"}},"title":"View"}}}